mkidpipeline-1.9.0.dist-info/METADATA
mkidpipeline-1.9.0.dist-info/WHEEL
mkidpipeline-1.9.0.dist-info/entry_points.txt
mkidpipeline/__init__.py
mkidpipeline/config.md
mkidpipeline/config.py
mkidpipeline/config/logging.yaml
mkidpipeline/data/dither_sample.log
mkidpipeline/data/sample_spectrum.txt
mkidpipeline/definitions.py
mkidpipeline/jsondefs.py
mkidpipeline/mkidpipe.py
mkidpipeline/photontable.py
mkidpipeline/pipeline.py
mkidpipeline/samples.py
mkidpipeline/steps/buildhdf.py
mkidpipeline/steps/cosmiccal.py
mkidpipeline/steps/drizzler.py
mkidpipeline/steps/flatcal.py
mkidpipeline/steps/lincal.py
mkidpipeline/steps/movies.py
mkidpipeline/steps/output.py
mkidpipeline/steps/pixcal.py
mkidpipeline/steps/sample.py
mkidpipeline/steps/speccal.py
mkidpipeline/steps/wavecal.py
mkidpipeline/steps/wcscal.py
mkidpipeline/tests/benchmark.py
mkidpipeline/tests/h5speed.py
mkidpipeline/tests/h5speed_data.yml
mkidpipeline/tests/h5speed_pipe.yml
mkidpipeline/tests/output_validation.py
mkidpipeline/tests/pipeline_output_timescales.zip
mkidpipeline/tests/test_config.py
mkidpipeline/tests/test_data.yml
mkidpipeline/tests/test_metadata.py
mkidpipeline/tests/test_wavecal.py
mkidpipeline/utils/__init__.py
mkidpipeline/utils/binparse.py
mkidpipeline/utils/conex2pixels.py
mkidpipeline/utils/fitting.py
mkidpipeline/utils/interpolating.py
mkidpipeline/utils/memory.py
mkidpipeline/utils/output_validation.py
mkidpipeline/utils/pdfs.py
mkidpipeline/utils/photometry.py
mkidpipeline/utils/plotting.py
mkidpipeline/utils/resampling.py
mkidpipeline/utils/smoothing.py
mkidpipeline/utils/snr.py
mkidpipeline/utils/wavecal_models.py
mkidpipeline-1.9.0.dist-info/RECORD
