Metadata-Version: 2.1
Name: mkidpipeline
Version: 1.9.0
Summary: Mazin Lab MKID Pipeline Utility
Author: Mazin Lab contributors
License: BSD-2-clause
Requires-Python: ~=3.10
Requires-Dist: mkidcore<2.0,>=1.9
Requires-Dist: setuptools>=72.2.0
Requires-Dist: numpy>=1.26
Requires-Dist: mpmath>=1.0.0
Requires-Dist: numexpr>=2.0.0
Requires-Dist: lmfit>=1.3.0
Requires-Dist: SharedArray>=3.0.0
Requires-Dist: astropy>=5.0
Requires-Dist: astroquery>=0.4.7
Requires-Dist: specutils>=1.0
Requires-Dist: photutils>=1.13
Requires-Dist: scikit-image>=0.20.0
Requires-Dist: drizzle>=1.0
Requires-Dist: matplotlib>=3.5
Requires-Dist: cycler>=0.11
Requires-Dist: progressbar2>=4.0.0
Requires-Dist: psutil>=5.0.0
Requires-Dist: tables>=3.8.0
Requires-Dist: ruamel.yaml>0.18
Requires-Dist: PyQt5; extra == "gui"
Requires-Dist: PySide2; extra == "gui"
Provides-Extra: gui
